octaviaclient/__init__.py
octaviaclient/version.py
octaviaclient/api/__init__.py
octaviaclient/api/constants.py
octaviaclient/api/exceptions.py
octaviaclient/api/v2/__init__.py
octaviaclient/api/v2/octavia.py
octaviaclient/hacking/__init__.py
octaviaclient/hacking/checks.py
octaviaclient/osc/__init__.py
octaviaclient/osc/plugin.py
octaviaclient/osc/v2/__init__.py
octaviaclient/osc/v2/amphora.py
octaviaclient/osc/v2/availabilityzone.py
octaviaclient/osc/v2/availabilityzoneprofile.py
octaviaclient/osc/v2/constants.py
octaviaclient/osc/v2/flavor.py
octaviaclient/osc/v2/flavorprofile.py
octaviaclient/osc/v2/health_monitor.py
octaviaclient/osc/v2/l7policy.py
octaviaclient/osc/v2/l7rule.py
octaviaclient/osc/v2/listener.py
octaviaclient/osc/v2/load_balancer.py
octaviaclient/osc/v2/member.py
octaviaclient/osc/v2/pool.py
octaviaclient/osc/v2/provider.py
octaviaclient/osc/v2/quota.py
octaviaclient/osc/v2/utils.py
octaviaclient/osc/v2/validate.py
octaviaclient/tests/__init__.py
octaviaclient/tests/fakes.py
octaviaclient/tests/functional/__init__.py
octaviaclient/tests/functional/base.py
octaviaclient/tests/functional/osc/__init__.py
octaviaclient/tests/functional/osc/v2/__init__.py
octaviaclient/tests/unit/__init__.py
octaviaclient/tests/unit/test_hacking.py
octaviaclient/tests/unit/api/__init__.py
octaviaclient/tests/unit/api/test_octavia.py
octaviaclient/tests/unit/osc/__init__.py
octaviaclient/tests/unit/osc/v2/__init__.py
octaviaclient/tests/unit/osc/v2/constants.py
octaviaclient/tests/unit/osc/v2/fakes.py
octaviaclient/tests/unit/osc/v2/test_amphora.py
octaviaclient/tests/unit/osc/v2/test_availabilityzone.py
octaviaclient/tests/unit/osc/v2/test_availabilityzoneprofile.py
octaviaclient/tests/unit/osc/v2/test_flavor.py
octaviaclient/tests/unit/osc/v2/test_flavorprofile.py
octaviaclient/tests/unit/osc/v2/test_health_monitor.py
octaviaclient/tests/unit/osc/v2/test_l7policy.py
octaviaclient/tests/unit/osc/v2/test_l7rule.py
octaviaclient/tests/unit/osc/v2/test_listener.py
python_octaviaclient-3.12.0.dist-info/AUTHORS
python_octaviaclient-3.12.0.dist-info/LICENSE
python_octaviaclient-3.12.0.dist-info/METADATA
python_octaviaclient-3.12.0.dist-info/WHEEL
python_octaviaclient-3.12.0.dist-info/entry_points.txt
python_octaviaclient-3.12.0.dist-info/pbr.json
python_octaviaclient-3.12.0.dist-info/top_level.txt
python_octaviaclient-3.12.0.dist-info/RECORD
