Metadata-Version: 2.1
Name: python-octaviaclient
Version: 3.12.0
Summary: Octavia client for OpenStack Load Balancing
Home-page: https://docs.openstack.org/python-octaviaclient/latest/
Author: OpenStack
Author-email: openstack-discuss@lists.openstack.org
Classifier: Environment :: OpenStack
Classifier: Intended Audience :: Information Technology
Classifier: Intended Audience :: System Administrators
Classifier: License :: OSI Approved :: Apache Software License
Classifier: Operating System :: POSIX :: Linux
Classifier: Programming Language :: Python
Classifier: Programming Language :: Python :: Implementation :: CPython
Classifier: Programming Language :: Python :: 3 :: Only
Classifier: Programming Language :: Python :: 3
Classifier: Programming Language :: Python :: 3.10
Classifier: Programming Language :: Python :: 3.11
Classifier: Programming Language :: Python :: 3.12
Requires-Python: >=3.10
License-File: LICENSE
Requires-Dist: cliff!=2.9.0,>=2.8.0
Requires-Dist: keystoneauth1>=3.18.0
Requires-Dist: python-neutronclient>=6.7.0
Requires-Dist: python-openstackclient>=3.12.0
Requires-Dist: osc-lib>=1.14.1
Requires-Dist: oslo.serialization!=2.19.1,>=2.18.0
Requires-Dist: oslo.utils>=3.33.0
Requires-Dist: pbr!=2.1.0,>=2.0.0
Requires-Dist: requests>=2.14.2
